kismetdb/__init__.py
kismetdb/alerts.py
kismetdb/base_interface.py
kismetdb/data_packets.py
kismetdb/data_sources.py
kismetdb/devices.py
kismetdb/kismet.py
kismetdb/packets.py
kismetdb/snapshots.py
kismetdb/utility.py
kismetdb/scripts/__init__.py
kismetdb/scripts/log_devices_to_filebeat_json.py
kismetdb/scripts/log_devices_to_json.py
kismetdb/scripts/log_to_csv.py
kismetdb/scripts/log_to_kml.py
kismetdb/scripts/log_to_pcap.py
kismetdb-2021.6.1.dist-info/LICENSE
kismetdb-2021.6.1.dist-info/METADATA
kismetdb-2021.6.1.dist-info/WHEEL
kismetdb-2021.6.1.dist-info/entry_points.txt
kismetdb-2021.6.1.dist-info/top_level.txt
kismetdb-2021.6.1.dist-info/RECORD
