Metadata-Version: 2.1
Name: kismetdb
Version: 2021.6.1
Summary: A python wrapper for the Kismet database
Home-page: https://github.com/kismetwireless/python-kismet-db
Author: Mike Kershaw, Ash Wilson
Author-email: dragorn@kismetwireless.net
License: GPL2
Keywords: kismet
Platform: UNKNOWN
Classifier: Development Status :: 5 - Production/Stable
Classifier: Intended Audience :: Developers
Classifier: Operating System :: MacOS :: MacOS X
Classifier: Operating System :: POSIX :: Linux
Classifier: Programming Language :: Python :: 2.7
Classifier: Programming Language :: Python :: 3.6
Classifier: Programming Language :: Python :: 3.7
Classifier: Topic :: Security
Classifier: License :: OSI Approved :: BSD License
Requires-Dist: python-dateutil
Requires-Dist: simplekml
